delugewebbrowser/__init__.py
delugewebbrowser/common.py
delugewebbrowser/core.py
delugewebbrowser/gtkui.py
delugewebbrowser/webui.py
delugewebbrowser/libraries/SimpleAuthServer.py
delugewebbrowser/libraries/Zipping.py
delugewebbrowser/libraries/__init__.py
DelugeWebBrowser-0.1.2.dist-info/LICENSE
DelugeWebBrowser-0.1.2.dist-info/METADATA
DelugeWebBrowser-0.1.2.dist-info/WHEEL
DelugeWebBrowser-0.1.2.dist-info/entry_points.txt
DelugeWebBrowser-0.1.2.dist-info/top_level.txt
DelugeWebBrowser-0.1.2.dist-info/RECORD
